install/__init__.py
install/createKernel.py
install/generate.py
install/pixiedustapp.py
pixiedust_optimus/__init__.py
pixiedust_optimus/proxyShell.py
pixiedust_optimus/apps/__init__.py
pixiedust_optimus/apps/cfBrowser.py
pixiedust_optimus/apps/cloudantBrowser.py
pixiedust_optimus/apps/connectionWidget.py
pixiedust_optimus/apps/mapboxBase.py
pixiedust_optimus/apps/mongoBrowser.py
pixiedust_optimus/apps/messageHub/__init__.py
pixiedust_optimus/apps/messageHub/messageHubApp.py
pixiedust_optimus/apps/watsonML/__init__.py
pixiedust_optimus/apps/watsonML/watsonMLApp.py
pixiedust_optimus/display/__init__.py
pixiedust_optimus/display/display.py
pixiedust_optimus/display/app/__init__.py
pixiedust_optimus/display/app/pixieapp.py
pixiedust_optimus/display/chart/__init__.py
pixiedust_optimus/display/chart/colorManager.py
pixiedust_optimus/display/chart/display.py
pixiedust_optimus/display/chart/plugins/__init__.py
pixiedust_optimus/display/chart/plugins/chart.py
pixiedust_optimus/display/chart/plugins/dialog.py
pixiedust_optimus/display/chart/plugins/elementInfo.py
pixiedust_optimus/display/chart/renderers/__init__.py
pixiedust_optimus/display/chart/renderers/baseChartDisplay.py
pixiedust_optimus/display/chart/renderers/commonOptions.py
pixiedust_optimus/display/chart/renderers/bokeh/__init__.py
pixiedust_optimus/display/chart/renderers/bokeh/barChartDisplay.py
pixiedust_optimus/display/chart/renderers/bokeh/bokehBaseDisplay.py
pixiedust_optimus/display/chart/renderers/bokeh/histogramDisplay.py
pixiedust_optimus/display/chart/renderers/bokeh/lineChartDisplay.py
pixiedust_optimus/display/chart/renderers/bokeh/scatterPlotDisplay.py
pixiedust_optimus/display/chart/renderers/google/__init__.py
pixiedust_optimus/display/chart/renderers/google/googleBaseDisplay.py
pixiedust_optimus/display/chart/renderers/google/googleMapDisplay.py
pixiedust_optimus/display/chart/renderers/google/templates/mapView.html
pixiedust_optimus-1.4.0.dist-info/DESCRIPTION.rst
pixiedust_optimus-1.4.0.dist-info/METADATA
pixiedust_optimus-1.4.0.dist-info/RECORD
pixiedust_optimus-1.4.0.dist-info/WHEEL
pixiedust_optimus-1.4.0.dist-info/metadata.json
pixiedust_optimus-1.4.0.dist-info/top_level.txt
